authorstyle/__init__.py
authorstyle/analyze.py
authorstyle/clustering.py
authorstyle/corpus.py
authorstyle/extract.py
authorstyle/text.py
authorstyle/features/__init__.py
authorstyle/features/lexical_features.py
authorstyle/features/readability.py
authorstyle/features/stylometric_features.py
authorstyle/features/util.py
authorstyle/features/external_data/functionwords.txt
authorstyle/features/external_data/word_class_mapping.txt
authorstyle/preprocessing/__init__.py
authorstyle/preprocessing/util.py
authorstyle-0.2.dist-info/LICENSE
authorstyle-0.2.dist-info/METADATA
authorstyle-0.2.dist-info/WHEEL
authorstyle-0.2.dist-info/top_level.txt
authorstyle-0.2.dist-info/RECORD
